README.md
setup.cfg
setup.py
hummer/__init__.py
hummer/setting.py
hummer.egg-info/PKG-INFO
hummer.egg-info/SOURCES.txt
hummer.egg-info/dependency_links.txt
hummer.egg-info/requires.txt
hummer.egg-info/top_level.txt
hummer/downloader/__init__.py
hummer/downloader/async.py
hummer/downloader/base.py
hummer/filter/__init__.py
hummer/pipeline/__init__.py
hummer/pipeline/base.py
hummer/scheduler/__init__.py
hummer/scheduler/base.py
hummer/scheduler/queue.py
hummer/scheduler/redis.py
hummer/spider/__init__.py
hummer/spider/base.py
hummer/spider/crawl.py
hummer/spider/simple.py
hummer/utils/__init__.py
hummer/utils/call.py